annb/__init__.py
annb/cli.py
annb/config.py
annb/envs.py
annb/indexes.py
annb/plot.py
annb/result.py
annb/runner.py
annb/anns/faiss/deploy.py
annb/anns/faiss/indexes.py
annb/anns/milvus/deploy.py
annb/anns/milvus/indexes.py
annb/dataset/__init__.py
annb/dataset/base_dataset.py
annb/dataset/hdf5_dataset.py
annb/dataset/random_dataset.py
annb/dataset/utils.py
annb-0.1.22.dist-info/LICENSE
annb-0.1.22.dist-info/METADATA
annb-0.1.22.dist-info/WHEEL
annb-0.1.22.dist-info/entry_points.txt
annb-0.1.22.dist-info/top_level.txt
annb-0.1.22.dist-info/RECORD
