Metadata-Version: 2.1
Name: annb
Version: 0.1.22
Summary: A simple ANN benchmark tools
Home-page: https://github.com/matrixji/annb
Author: Ji Bin
Author-email: matrixji@live.com
License: Apache-2.0
Keywords: ANN benchmark,Test tools
Requires-Python: >=3.6
License-File: LICENSE
Requires-Dist: h5py
Requires-Dist: numpy
Requires-Dist: scikit-learn
Requires-Dist: docker
Requires-Dist: PyYAML
Requires-Dist: matplotlib
